[{"__type__":"cc.SpriteFrame","content":{"name":"tips07","texture":"d80lLEI91DNroc7wfuOhFa","rect":[1,877,1007,144],"offset":[0,0],"originalSize":[1007,144],"capInsets":[0,0,0,0]}},{"__type__":"cc.SpriteFrame","content":{"name":"tips06","texture":"d80lLEI91DNroc7wfuOhFa","rect":[1,731,1007,144],"offset":[0,0],"originalSize":[1007,144],"capInsets":[0,0,0,0]}},{"__type__":"cc.SpriteFrame","content":{"name":"tips03","texture":"d80lLEI91DNroc7wfuOhFa","rect":[1,293,1007,144],"offset":[0,0],"originalSize":[1007,144],"capInsets":[0,0,0,0]}},{"__type__":"cc.SpriteFrame","content":{"name":"tips04","texture":"d80lLEI91DNroc7wfuOhFa","rect":[1,439,1007,144],"offset":[0,0],"originalSize":[1007,144],"capInsets":[0,0,0,0]}},{"__type__":"cc.SpriteFrame","content":{"name":"tips02","texture":"d80lLEI91DNroc7wfuOhFa","rect":[1,147,1007,144],"offset":[0,0],"originalSize":[1007,144],"capInsets":[0,0,0,0]}},{"__type__":"cc.SpriteFrame","content":{"name":"tips05","texture":"d80lLEI91DNroc7wfuOhFa","rect":[1,585,1007,144],"offset":[0,0],"originalSize":[1007,144],"capInsets":[0,0,0,0]}},{"__type__":"cc.SpriteAtlas","_name":"tips.plist","_spriteFrames":{"tips01":{"__uuid__":"f483HvpUhJCbs69oGq37WL"},"tips02":{"__uuid__":"78fo9KIXVDQYph90awWOhh"},"tips03":{"__uuid__":"64xRb3NxtB04AkqYOyyz1z"},"tips04":{"__uuid__":"66Bn9xmA9L1pf79rUT2e5Q"},"tips05":{"__uuid__":"92anQy/CJMIrrgMCLvjNwp"},"tips06":{"__uuid__":"49vf/klJ9Olo4QVQWDN6vn"},"tips07":{"__uuid__":"1fDbABsn5PgpB65J6JlyiD"}}},{"__type__":"cc.SpriteFrame","content":{"name":"tips01","texture":"d80lLEI91DNroc7wfuOhFa","rect":[1,1,1007,144],"offset":[0,0],"originalSize":[1007,144],"capInsets":[0,0,0,0]}}]